insightminer/__init__.py
insightminer/main.py
insightminer/prompts.py
insightminer-2025.12.21123144.dist-info/METADATA
insightminer-2025.12.21123144.dist-info/WHEEL
insightminer-2025.12.21123144.dist-info/top_level.txt
insightminer-2025.12.21123144.dist-info/RECORD
