Metadata-Version: 2.4
Name: insightminer
Version: 2025.12.21123144
Summary: A new package designed to extract and structure key insights from opinionated articles or social media posts. The package takes a text input, such as a blog post or a tweet, and uses llmatch-messages
Author-email: insightminer <hi@eugene.plus>
License: MIT
Project-URL: Homepage, https://github.com/chigwell/insightminer
Requires-Python: >=3.9
Requires-Dist: langchain-llm7>=0.0.0
Requires-Dist: llmatch-messages>=0.0.0
Requires-Dist: langchain-core>=0.3.0
